exc/__init__.py
exc/test.py
exc-0.92.dist-info/METADATA
exc-0.92.dist-info/RECORD
exc-0.92.dist-info/WHEEL
exc-0.92.dist-info/top_level.txt
meta_exc/__init__.py
meta_exc/test.py
